[
  {
    "_id": "rec0bpI6OkgZsykSB",
    "active": true,
    "areaOfWorkAllocated": "Central Coordination",
    "competenceBackground": "Social Work",
    "id": "rec0bpI6OkgZsykSB",
    "location": "South Delhi",
    "name": "Vikrant Abrol"
  },
  {
    "_id": "rec24I5mDTmwq0jnh",
    "active": true,
    "areaOfWorkAllocated": "MIS Management",
    "competenceBackground": "Social Work",
    "id": "rec24I5mDTmwq0jnh",
    "location": "Dehradun",
    "name": "Abhijit Patwal",
    "reference": "Mr. Anurag Kashayp"
  },
  {
    "_id": "rec4KettqbIcPbESo",
    "active": true,
    "areaOfWorkAllocated": "Procurement",
    "distribution": [
      "rec0bAwdiR6IYFSoM",
      "rec9F69PL70oGxW4s",
      "recwjSm6Yv4o25X2t",
      "recRFVdEzaRc7xu4v"
    ],
    "id": "rec4KettqbIcPbESo",
    "name": "Atul Celly",
    "procurement": [
      "recwCEwSWdCOrV6Oy",
      "recgp3LH7xoeA6SSm",
      "recv5UWbb8XBHLbF4",
      "recAj1cTxS0EdKwGU"
    ]
  },
  {
    "_id": "rec5zct2LXj2cThee",
    "active": true,
    "areaOfWorkAllocated": "Day to Day Coordination",
    "competenceBackground": "Social Work",
    "id": "rec5zct2LXj2cThee",
    "location": "Dehradun",
    "name": "Maneet Madan"
  },
  {
    "_id": "rec8weJ5mIvcvV5rK",
    "active": true,
    "areaOfWorkAllocated": "Sec 37, Gurgaon Warehouse Management",
    "distribution": [
      "recdDc22z8gLjTCqa"
    ],
    "id": "rec8weJ5mIvcvV5rK",
    "name": "Ramveer Singh",
    "socialMediaOutreach": [
      "recdBp0m9EO8WyKZs"
    ]
  },
  {
    "_id": "recI4lLcOHd2rv3gk",
    "active": true,
    "areaOfWorkAllocated": "Day to Day Coordination",
    "competenceBackground": "Social Work",
    "id": "recI4lLcOHd2rv3gk",
    "location": "New Delhi (Jamia)",
    "name": "Iqbal Mohammed"
  },
  {
    "_id": "recI5SecmybSlU6Ul",
    "active": true,
    "areaOfWorkAllocated": "Technology and Social Media",
    "competenceBackground": "Technology, Startups",
    "id": "recI5SecmybSlU6Ul",
    "location": "South Delhi",
    "name": "Anand Chowdhary"
  },
  {
    "_id": "recIKJzr77ClSkBIp",
    "active": true,
    "areaOfWorkAllocated": "Technology and Coordination",
    "competenceBackground": "Technology",
    "distribution": [
      "recV6TQvYM1Xyyn6f",
      "recgx674hicH6ct0e",
      "recLsoT0ugKuhHqiZ",
      "recEAKS9kmh01mXrg"
    ],
    "id": "recIKJzr77ClSkBIp",
    "location": "West Delhi",
    "name": "Shivek Khurana",
    "socialMediaOutreach": [
      "recMldiWLslcoAWQv"
    ],
    "volunteerOnboarding": [
      "recgplSxhP0Gc6L8b",
      "recN1fgBREpQXrOf9"
    ]
  },
  {
    "_id": "recJbFfMkoYdLLhMv",
    "active": true,
    "competenceBackground": "Corporate Law",
    "distribution": [
      "recPUwpqML3yylCUW"
    ],
    "id": "recJbFfMkoYdLLhMv",
    "location": "West Delhi",
    "name": "Sunei Kapur"
  },
  {
    "_id": "recKiQ0VGnZMljPTf",
    "active": true,
    "areaOfWorkAllocated": "Distribution",
    "distribution": [
      "recLwT1DazwdakLbx"
    ],
    "id": "recKiQ0VGnZMljPTf",
    "name": "Kripa Jayaram",
    "socialMediaOutreach": [
      "recOGr4pWVWy0xYEW"
    ]
  },
  {
    "_id": "recWWljtJfSWy1CLq",
    "active": true,
    "areaOfWorkAllocated": "Technology",
    "competenceBackground": "Technology",
    "id": "recWWljtJfSWy1CLq",
    "location": "Noida",
    "name": "Rohit Bhatia"
  },
  {
    "_id": "recfrqQ5kwqYlZn1I",
    "active": true,
    "areaOfWorkAllocated": "Accounting",
    "competenceBackground": "Accounts, logistics",
    "id": "recfrqQ5kwqYlZn1I",
    "location": "Dwarka",
    "name": "Madan Singh",
    "reference": "Anurag"
  },
  {
    "_id": "rech2UBwigIWZXTOJ",
    "active": true,
    "areaOfWorkAllocated": "Documentation",
    "competenceBackground": "Food technology, Social work",
    "id": "rech2UBwigIWZXTOJ",
    "location": "Mumbai",
    "name": "Tuhin",
    "reference": "Mr. Anurag Kashayp"
  },
  {
    "_id": "recjDkPJ6t8RVHZXz",
    "active": true,
    "areaOfWorkAllocated": "Social Media Outreach",
    "id": "recjDkPJ6t8RVHZXz",
    "location": "West Delhi",
    "name": "Sarthak Khurana"
  },
  {
    "_id": "reck2YKHsRElZlcOg",
    "active": true,
    "areaOfWorkAllocated": "Distribution",
    "competenceBackground": "Social work",
    "distribution": [
      "rec3WRRvrLxq90FmI"
    ],
    "id": "reck2YKHsRElZlcOg",
    "location": "South Delhi",
    "name": "Anurag Kashyap"
  },
  {
    "_id": "recqBYmavbpZ8YJIE",
    "active": true,
    "areaOfWorkAllocated": "Social Media",
    "competenceBackground": "Writing, Publishing",
    "id": "recqBYmavbpZ8YJIE",
    "location": "South Delhi",
    "name": "Sukriti Kapoor"
  },
  {
    "_id": "recsPBGQa7pGKLwl6",
    "active": true,
    "areaOfWorkAllocated": "Government Relationship and E Passes",
    "id": "recsPBGQa7pGKLwl6",
    "name": "Ravinder Dagar"
  },
  {
    "_id": "recu3FXtA5MK6a9X0",
    "active": true,
    "areaOfWorkAllocated": "Volunteer Coordination",
    "id": "recu3FXtA5MK6a9X0",
    "location": "South Delhi",
    "name": "Radha Chowdhary"
  },
  {
    "_id": "reczU90mrNHyCOXdK",
    "active": true,
    "areaOfWorkAllocated": "Day to Day Coordination",
    "competenceBackground": "Social Work",
    "id": "reczU90mrNHyCOXdK",
    "location": "Noida & New Delhi",
    "name": "Alokesh Sharma"
  }
]
